{
  "repo": {
    "timestamp": 1728619309000
  },
  "packages": {
    "app.organicmaps": {
      "metadata": {
        "added": 1728446507000,
        "lastUpdated": 1728446507000
      },
      "versions": {
        "e39f017a1a9f9a6d1ecae7c95e902e1ba94cdcc24994dcf0be2140f608c90da3": null,
        "c61ce7886dae13d2e9f24c68b7fb9d7b2b9d61062d76a675a1f1dc6f8c351fcc": {
          "added": 1728446507000,
          "file": {
            "name": "/OrganicMaps.apk",
            "sha256": "c61ce7886dae13d2e9f24c68b7fb9d7b2b9d61062d76a675a1f1dc6f8c351fcc",
            "size": 57619996
          },
          "manifest": {
            "nativecode": [
              "arm64-v8a",
              "armeabi-v7a",
              "x86_64"
            ],
            "versionName": "2024.10.04-7-FDroid",
            "versionCode": 24100407,
            "usesSdk": {
              "minSdkVersion": 21,
              "targetSdkVersion": 35
            },
            "signer": {
              "sha256": [
                "e216fc386c327ec88d056026f1dea27be2bc3f9d7ee956e4361c4b64ec459fe9"
              ]
            },
            "usesPermission": [
              {
                "name": "android.permission.ACCESS_COARSE_LOCATION"
              },
              {
                "name": "android.permission.ACCESS_FINE_LOCATION"
              },
              {
                "name": "android.permission.ACCESS_LOCATION_EXTRA_COMMANDS"
              },
              {
                "name": "android.permission.INTERNET"
              },
              {
                "name": "android.permission.ACCESS_NETWORK_STATE"
              },
              {
                "name": "android.permission.WAKE_LOCK"
              },
              {
                "name": "android.permission.FOREGROUND_SERVICE"
              },
              {
                "name": "android.permission.FOREGROUND_SERVICE_LOCATION"
              },
              {
                "name": "android.permission.FOREGROUND_SERVICE_SPECIAL_USE"
              },
              {
                "name": "android.permission.POST_NOTIFICATIONS"
              },
              {
                "name": "androidx.car.app.NAVIGATION_TEMPLATES"
              },
              {
                "name": "androidx.car.app.ACCESS_SURFACE"
              },
              {
                "name": "android.permission.RECEIVE_BOOT_COMPLETED"
              },
              {
                "name": "app.organicmaps.DYNAMIC_RECEIVER_NOT_EXPORTED_PERMISSION"
              }
            ]
          }
        }
      }
    },
    "com.aurora.store": {
      "metadata": {
        "added": 1728619302000,
        "lastUpdated": 1728619302000
      },
      "versions": {
        "5a5c56f59194d973d335a534b0e359659e1bf49a8ecb8188bf8c2f8d6c68ffaa": null,
        "835c59db2017feb7659ac5623aa52ad15eba9fe652ec03bab9872da5ec31cead": {
          "added": 1728619302000,
          "file": {
            "name": "/AuroraStore.apk",
            "sha256": "835c59db2017feb7659ac5623aa52ad15eba9fe652ec03bab9872da5ec31cead",
            "size": 7387686
          },
          "manifest": {
            "nativecode": [
              "arm64-v8a",
              "armeabi-v7a",
              "x86",
              "x86_64"
            ],
            "versionName": "4.6.1",
            "versionCode": 62,
            "usesSdk": {
              "minSdkVersion": 21,
              "targetSdkVersion": 35
            },
            "signer": {
              "sha256": [
                "5c83c7672b929955dc0a1db89a5e6ae4389e2eae7ec939956041694e5815f532"
              ]
            },
            "usesPermission": [
              {
                "name": "android.permission.INTERNET"
              },
              {
                "name": "android.permission.ACCESS_NETWORK_STATE"
              },
              {
                "name": "android.permission.FOREGROUND_SERVICE"
              },
              {
                "name": "android.permission.FOREGROUND_SERVICE_DATA_SYNC"
              },
              {
                "name": "android.permission.REQUEST_IGNORE_BATTERY_OPTIMIZATIONS"
              },
              {
                "name": "android.permission.MANAGE_EXTERNAL_STORAGE"
              },
              {
                "name": "android.permission.READ_EXTERNAL_STORAGE"
              },
              {
                "name": "android.permission.WRITE_EXTERNAL_STORAGE"
              },
              {
                "name": "android.permission.QUERY_ALL_PACKAGES"
              },
              {
                "name": "android.permission.INSTALL_PACKAGES"
              },
              {
                "name": "android.permission.DELETE_PACKAGES"
              },
              {
                "name": "android.permission.REQUEST_INSTALL_PACKAGES"
              },
              {
                "name": "android.permission.REQUEST_DELETE_PACKAGES"
              },
              {
                "name": "android.permission.ENFORCE_UPDATE_OWNERSHIP"
              },
              {
                "name": "android.permission.UPDATE_PACKAGES_WITHOUT_USER_ACTION"
              },
              {
                "name": "android.permission.POST_NOTIFICATIONS"
              },
              {
                "name": "android.permission.WAKE_LOCK"
              },
              {
                "name": "android.permission.RECEIVE_BOOT_COMPLETED"
              },
              {
                "name": "com.aurora.store.DYNAMIC_RECEIVER_NOT_EXPORTED_PERMISSION"
              },
              {
                "name": "moe.shizuku.manager.permission.API_V23"
              }
            ]
          },
          "antiFeatures": {
            "NonFreeNet": {}
          }
        }
      }
    },
    "org.thoughtcrime.securesms": {
      "metadata": {
        "added": 1728619308000,
        "lastUpdated": 1728619308000
      },
      "versions": {
        "ce64a9dacdc9bde4b9e184fb1911b504f8fc8ad2f60d0e30e65274d76f1b5719": null,
        "df0de04a24a00b34a609ca43b404e786e63a4d23d568a7a801c5d2aee3036642": {
          "added": 1728619308000,
          "file": {
            "name": "/Signal.apk",
            "sha256": "df0de04a24a00b34a609ca43b404e786e63a4d23d568a7a801c5d2aee3036642",
            "size": 100285593
          },
          "manifest": {
            "nativecode": [
              "arm64-v8a",
              "armeabi-v7a",
              "x86",
              "x86_64"
            ],
            "versionName": "7.19.2",
            "versionCode": 146800,
            "usesSdk": {
              "minSdkVersion": 21,
              "targetSdkVersion": 34
            },
            "signer": {
              "sha256": [
                "29f34e5f27f211b424bc5bf9d67162c0eafba2da35af35c16416fc446276ba26"
              ]
            },
            "usesPermission": [
              {
                "name": "android.permission.DOWNLOAD_WITHOUT_NOTIFICATION"
              },
              {
                "name": "android.permission.REQUEST_INSTALL_PACKAGES"
              },
              {
                "name": "android.permission.UPDATE_PACKAGES_WITHOUT_USER_ACTION"
              },
              {
                "name": "android.permission.USE_FINGERPRINT"
              },
              {
                "name": "org.thoughtcrime.securesms.ACCESS_SECRETS"
              },
              {
                "name": "android.permission.READ_PROFILE"
              },
              {
                "name": "android.permission.READ_CONTACTS"
              },
              {
                "name": "android.permission.WRITE_CONTACTS"
              },
              {
                "name": "android.permission.ACCESS_NOTIFICATION_POLICY"
              },
              {
                "name": "android.permission.READ_PHONE_STATE"
              },
              {
                "name": "android.permission.READ_PHONE_NUMBERS"
              },
              {
                "name": "android.permission.WRITE_EXTERNAL_STORAGE",
                "maxSdkVersion": 28
              },
              {
                "name": "android.permission.CAMERA"
              },
              {
                "name": "android.permission.ACCESS_COARSE_LOCATION"
              },
              {
                "name": "android.permission.ACCESS_FINE_LOCATION"
              },
              {
                "name": "android.permission.NEARBY_WIFI_DEVICES"
              },
              {
                "name": "android.permission.RECORD_AUDIO"
              },
              {
                "name": "android.permission.MODIFY_AUDIO_SETTINGS"
              },
              {
                "name": "android.permission.READ_CALL_STATE"
              },
              {
                "name": "android.permission.RECEIVE_BOOT_COMPLETED"
              },
              {
                "name": "android.permission.VIBRATE"
              },
              {
                "name": "android.permission.ACCESS_NETWORK_STATE"
              },
              {
                "name": "android.permission.WAKE_LOCK"
              },
              {
                "name": "android.permission.INTERNET"
              },
              {
                "name": "android.permission.FOREGROUND_SERVICE"
              },
              {
                "name": "android.permission.GET_ACCOUNTS"
              },
              {
                "name": "android.permission.READ_SYNC_SETTINGS"
              },
              {
                "name": "android.permission.WRITE_SYNC_SETTINGS"
              },
              {
                "name": "android.permission.AUTHENTICATE_ACCOUNTS"
              },
              {
                "name": "android.permission.USE_CREDENTIALS"
              },
              {
                "name": "android.permission.INSTALL_SHORTCUT"
              },
              {
                "name": "com.android.launcher.permission.INSTALL_SHORTCUT"
              },
              {
                "name": "android.permission.ACCESS_WIFI_STATE"
              },
              {
                "name": "android.permission.CHANGE_WIFI_STATE"
              },
              {
                "name": "android.permission.CHANGE_NETWORK_STATE"
              },
              {
                "name": "android.permission.BLUETOOTH"
              },
              {
                "name": "android.permission.BROADCAST_STICKY"
              },
              {
                "name": "android.permission.DISABLE_KEYGUARD"
              },
              {
                "name": "android.permission.RAISED_THREAD_PRIORITY"
              },
              {
                "name": "android.permission.REQUEST_IGNORE_BATTERY_OPTIMIZATIONS"
              },
              {
                "name": "android.permission.USE_FULL_SCREEN_INTENT"
              },
              {
                "name": "android.permission.MANAGE_OWN_CALLS"
              },
              {
                "name": "android.permission.SCHEDULE_EXACT_ALARM"
              },
              {
                "name": "android.permission.POST_NOTIFICATIONS"
              },
              {
                "name": "android.permission.READ_MEDIA_IMAGES"
              },
              {
                "name": "android.permission.READ_MEDIA_VIDEO"
              },
              {
                "name": "android.permission.READ_MEDIA_VISUAL_USER_SELECTED"
              },
              {
                "name": "android.permission.FOREGROUND_SERVICE_REMOTE_MESSAGING"
              },
              {
                "name": "android.permission.FOREGROUND_SERVICE_DATA_SYNC"
              },
              {
                "name": "android.permission.FOREGROUND_SERVICE_MEDIA_PLAYBACK"
              },
              {
                "name": "android.permission.FOREGROUND_SERVICE_MICROPHONE"
              },
              {
                "name": "android.permission.FOREGROUND_SERVICE_PHONE_CALL"
              },
              {
                "name": "android.permission.FOREGROUND_SERVICE_CONNECTED_DEVICE"
              },
              {
                "name": "android.permission.USE_BIOMETRIC"
              },
              {
                "name": "com.google.android.c2dm.permission.RECEIVE"
              },
              {
                "name": "org.thoughtcrime.securesms.DYNAMIC_RECEIVER_NOT_EXPORTED_PERMISSION"
              },
              {
                "name": "android.permission.READ_EXTERNAL_STORAGE"
              },
              {
                "name": "com.sec.android.provider.badge.permission.READ"
              },
              {
                "name": "com.sec.android.provider.badge.permission.WRITE"
              },
              {
                "name": "com.htc.launcher.permission.READ_SETTINGS"
              },
              {
                "name": "com.htc.launcher.permission.UPDATE_SHORTCUT"
              },
              {
                "name": "com.sonyericsson.home.permission.BROADCAST_BADGE"
              },
              {
                "name": "com.sonymobile.home.permission.PROVIDER_INSERT_BADGE"
              },
              {
                "name": "com.anddoes.launcher.permission.UPDATE_COUNT"
              },
              {
                "name": "com.majeur.launcher.permission.UPDATE_BADGE"
              },
              {
                "name": "com.huawei.android.launcher.permission.CHANGE_BADGE"
              },
              {
                "name": "com.huawei.android.launcher.permission.READ_SETTINGS"
              },
              {
                "name": "com.huawei.android.launcher.permission.WRITE_SETTINGS"
              },
              {
                "name": "android.permission.READ_APP_BADGE"
              },
              {
                "name": "com.oppo.launcher.permission.READ_SETTINGS"
              },
              {
                "name": "com.oppo.launcher.permission.WRITE_SETTINGS"
              },
              {
                "name": "me.everything.badger.permission.BADGE_COUNT_READ"
              },
              {
                "name": "me.everything.badger.permission.BADGE_COUNT_WRITE"
              }
            ]
          }
        }
      }
    },
    "org.torproject.torbrowser": {
      "metadata": {
        "added": 1728532922000,
        "lastUpdated": 1728532922000
      },
      "versions": {
        "82bb602b5dc9e42f0e513649ff102754128aebc9dc62965702e0c7ab8962ef59": null,
        "9ec4b2c004b4038eb6b67cd6d39a193cfac5e075a3500ae4c08f51449c4cfaf8": {
          "added": 1728532922000,
          "file": {
            "name": "/TorBrowser.apk",
            "sha256": "9ec4b2c004b4038eb6b67cd6d39a193cfac5e075a3500ae4c08f51449c4cfaf8",
            "size": 101737146
          },
          "manifest": {
            "nativecode": [
              "arm64-v8a"
            ],
            "versionName": "115.2.1-release (13.5.7)",
            "versionCode": 2016049043,
            "usesSdk": {
              "minSdkVersion": 21,
              "targetSdkVersion": 33
            },
            "signer": {
              "sha256": [
                "20061f045e737c67375c17794cfedb436a03cec6bacb7cb9f96642205ca2cec8"
              ]
            },
            "usesPermission": [
              {
                "name": "android.permission.INTERNET"
              },
              {
                "name": "android.permission.READ_EXTERNAL_STORAGE"
              },
              {
                "name": "android.permission.WRITE_EXTERNAL_STORAGE",
                "maxSdkVersion": 28
              },
              {
                "name": "android.permission.CAMERA"
              },
              {
                "name": "android.permission.RECORD_AUDIO"
              },
              {
                "name": "com.android.launcher.permission.INSTALL_SHORTCUT",
                "maxSdkVersion": 26
              },
              {
                "name": "android.permission.VIBRATE"
              },
              {
                "name": "android.permission.USE_BIOMETRIC"
              },
              {
                "name": "android.permission.QUERY_ALL_PACKAGES"
              },
              {
                "name": "android.permission.POST_NOTIFICATIONS"
              },
              {
                "name": "android.permission.READ_MEDIA_VIDEO"
              },
              {
                "name": "android.permission.READ_MEDIA_IMAGES"
              },
              {
                "name": "android.permission.READ_MEDIA_AUDIO"
              },
              {
                "name": "android.permission.FOREGROUND_SERVICE"
              },
              {
                "name": "android.permission.DOWNLOAD_WITHOUT_NOTIFICATION"
              },
              {
                "name": "android.permission.ACCESS_NETWORK_STATE"
              },
              {
                "name": "android.permission.USE_FINGERPRINT"
              },
              {
                "name": "android.permission.HIGH_SAMPLING_RATE_SENSORS"
              },
              {
                "name": "android.permission.WAKE_LOCK"
              },
              {
                "name": "android.permission.MODIFY_AUDIO_SETTINGS"
              },
              {
                "name": "com.google.android.c2dm.permission.RECEIVE"
              },
              {
                "name": "android.permission.RECEIVE_BOOT_COMPLETED"
              },
              {
                "name": "org.torproject.torbrowser.DYNAMIC_RECEIVER_NOT_EXPORTED_PERMISSION"
              },
              {
                "name": "com.google.android.finsky.permission.BIND_GET_INSTALL_REFERRER_SERVICE"
              }
            ],
            "usesPermissionSdk23": [
              {
                "name": "android.permission.REQUEST_INSTALL_PACKAGES"
              }
            ]
          }
        }
      }
    },
    "se.leap.riseupvpn": {
      "metadata": {
        "added": 1728446509000,
        "lastUpdated": 1728446509000
      },
      "versions": {
        "8b85ef9f718aa037da810ce72e9f86f20a5195c11a31c52c0e4ef5e6dbd102fe": null,
        "47c1b809d9545b67a7285230b3656ee4de7eecdcbe992a11ea24ea9739eacc2e": {
          "added": 1728446509000,
          "file": {
            "name": "/RiseupVPN.apk",
            "sha256": "47c1b809d9545b67a7285230b3656ee4de7eecdcbe992a11ea24ea9739eacc2e",
            "size": 63725960
          },
          "manifest": {
            "nativecode": [
              "arm64-v8a",
              "armeabi-v7a",
              "x86",
              "x86_64"
            ],
            "versionName": "1.4.1",
            "versionCode": 176000,
            "usesSdk": {
              "minSdkVersion": 21,
              "targetSdkVersion": 34
            },
            "signer": {
              "sha256": [
                "cd592617b27a65cd44e24fb7b8bc5d13d140fc790c37339eef4abb4518dd3ac2"
              ]
            },
            "usesPermission": [
              {
                "name": "android.permission.INTERNET"
              },
              {
                "name": "android.permission.ACCESS_NETWORK_STATE"
              },
              {
                "name": "android.permission.ACCESS_WIFI_STATE"
              },
              {
                "name": "android.permission.POST_NOTIFICATIONS"
              },
              {
                "name": "android.permission.RECEIVE_BOOT_COMPLETED"
              },
              {
                "name": "android.permission.VIBRATE"
              },
              {
                "name": "android.permission.WAKE_LOCK"
              },
              {
                "name": "android.permission.FOREGROUND_SERVICE"
              },
              {
                "name": "android.permission.FOREGROUND_SERVICE_SYSTEM_EXEMPTED"
              },
              {
                "name": "android.permission.FOREGROUND_SERVICE_DATA_SYNC"
              },
              {
                "name": "android.permission.WRITE_EXTERNAL_STORAGE"
              },
              {
                "name": "android.permission.QUERY_ALL_PACKAGES"
              },
              {
                "name": "se.leap.riseupvpn.DYNAMIC_RECEIVER_NOT_EXPORTED_PERMISSION"
              },
              {
                "name": "android.permission.READ_EXTERNAL_STORAGE"
              }
            ]
          }
        }
      }
    }
  }
}